speculate/__init__.py
speculate/cli.py
speculate/core.py
speculate/providers/__init__.py
speculate/providers/ollama_provider.py
speculate_llm-0.1.0.dist-info/METADATA
speculate_llm-0.1.0.dist-info/WHEEL
speculate_llm-0.1.0.dist-info/entry_points.txt
speculate_llm-0.1.0.dist-info/RECORD
