Metadata-Version: 2.4
Name: speculate-llm
Version: 0.1.0
Summary: Speculate is a BDD-style framework for validating LLM behavior, offering rich CLI reporting and support for multiple backends like Ollama, OpenAI, and more.
Project-URL: Homepage, https://github.com/digi-cazter/speculate
Project-URL: Repository, https://github.com/digi-cazter/speculate
Project-URL: Issues, https://github.com/digi-cazter/speculate/issues
Author-email: Donavan White <digi.cazter@gmail.com>
Maintainer-email: Donavan White <digi.cazter@gmail.com>
License: MIT
Keywords: BDD,LLM,Ollama,evaluation,pydantic,rich,testing
Classifier: Intended Audience :: Developers
Classifier: License :: OSI Approved :: MIT License
Classifier: Operating System :: OS Independent
Classifier: Programming Language :: Python :: 3
Classifier: Programming Language :: Python :: 3 :: Only
Classifier: Topic :: Software Development :: Testing
Requires-Python: >=3.9
Requires-Dist: pydantic>=2.7
Requires-Dist: requests>=2.31
Requires-Dist: rich>=13.7
